cookiecutter/VERSION.txt
cookiecutter/__init__.py
cookiecutter/__main__.py
cookiecutter/cli.py
cookiecutter/config.py
cookiecutter/environment.py
cookiecutter/exceptions.py
cookiecutter/extensions.py
cookiecutter/find.py
cookiecutter/generate.py
cookiecutter/hooks.py
cookiecutter/log.py
cookiecutter/main.py
cookiecutter/prompt.py
cookiecutter/replay.py
cookiecutter/repository.py
cookiecutter/utils.py
cookiecutter/vcs.py
cookiecutter/zipfile.py
cookiecutter-2.5.0.dist-info/AUTHORS.md
cookiecutter-2.5.0.dist-info/LICENSE
cookiecutter-2.5.0.dist-info/METADATA
cookiecutter-2.5.0.dist-info/WHEEL
cookiecutter-2.5.0.dist-info/entry_points.txt
cookiecutter-2.5.0.dist-info/top_level.txt
cookiecutter-2.5.0.dist-info/RECORD
