Metadata-Version: 2.1
Name: cookiecutter
Version: 2.5.0
Summary: A command-line utility that creates projects from project templates, e.g. creating a Python package project from a Python package project template.
Home-page: https://github.com/cookiecutter/cookiecutter
Author: Audrey Feldroy
Author-email: audreyr@gmail.com
License: BSD
Project-URL: Documentation, https://cookiecutter.readthedocs.io
Project-URL: Issues, https://github.com/cookiecutter/cookiecutter/issues
Project-URL: Discord, https://discord.gg/9BrxzPKuEW
Keywords: cookiecutter,Python,projects,project templates,Jinja2,skeleton,scaffolding,project directory,package,packaging
Classifier: Development Status :: 5 - Production/Stable
Classifier: Environment :: Console
Classifier: Intended Audience :: Developers
Classifier: Natural Language :: English
Classifier: License :: OSI Approved :: BSD License
Classifier: Programming Language :: Python :: 3 :: Only
Classifier: Programming Language :: Python :: 3
Classifier: Programming Language :: Python :: 3.7
Classifier: Programming Language :: Python :: 3.8
Classifier: Programming Language :: Python :: 3.9
Classifier: Programming Language :: Python :: 3.10
Classifier: Programming Language :: Python :: 3.11
Classifier: Programming Language :: Python :: Implementation :: CPython
Classifier: Programming Language :: Python :: Implementation :: PyPy
Classifier: Programming Language :: Python
Classifier: Topic :: Software Development
Requires-Python: >=3.7
License-File: LICENSE
License-File: AUTHORS.md
Requires-Dist: binaryornot>=0.4.4
Requires-Dist: Jinja2<4.0.0,>=2.7
Requires-Dist: click<9.0.0,>=7.0
Requires-Dist: pyyaml>=5.3.1
Requires-Dist: python-slugify>=4.0.0
Requires-Dist: requests>=2.23.0
Requires-Dist: arrow
Requires-Dist: rich
